LICENSE
MANIFEST.in
README.md
setup.py
tap_ga4/__init__.py
tap_ga4/client.py
tap_ga4/discover.py
tap_ga4/field_exclusions.json
tap_ga4/reports.py
tap_ga4/sync.py
tap_ga4.egg-info/PKG-INFO
tap_ga4.egg-info/SOURCES.txt
tap_ga4.egg-info/dependency_links.txt
tap_ga4.egg-info/entry_points.txt
tap_ga4.egg-info/requires.txt
tap_ga4.egg-info/top_level.txt
tests/test_all_fields.py
tests/test_automatic_fields.py
tests/test_bookmark.py
tests/test_discovery.py
tests/test_ga4_conversion_window.py
tests/test_ga4_conversion_window_invalid.py
tests/test_interrupted_sync.py
tests/test_pagination.py
tests/test_start_date.py
tests/test_sync_canary.py